odoo/addons/product_pricelist_brand_required/README.rst
odoo/addons/product_pricelist_brand_required/__init__.py
odoo/addons/product_pricelist_brand_required/__manifest__.py
odoo/addons/product_pricelist_brand_required/i18n/es.po
odoo/addons/product_pricelist_brand_required/models/__init__.py
odoo/addons/product_pricelist_brand_required/models/product_pricelist.py
odoo/addons/product_pricelist_brand_required/models/product_pricelist_item.py
odoo/addons/product_pricelist_brand_required/readme/CONFIGURE.md
odoo/addons/product_pricelist_brand_required/readme/CONTRIBUTORS.md
odoo/addons/product_pricelist_brand_required/readme/DESCRIPTION.md
odoo/addons/product_pricelist_brand_required/readme/USAGE.md
odoo/addons/product_pricelist_brand_required/static/description/icon.png
odoo/addons/product_pricelist_brand_required/static/description/index.html
odoo/addons/product_pricelist_brand_required/tests/__init__.py
odoo/addons/product_pricelist_brand_required/tests/test_product_pricelist_brand_required.py
odoo/addons/product_pricelist_brand_required/views/product_pricelist_views.xml
odoo_addon_product_pricelist_brand_required-17.0.2.0.0.dist-info/METADATA
odoo_addon_product_pricelist_brand_required-17.0.2.0.0.dist-info/WHEEL
odoo_addon_product_pricelist_brand_required-17.0.2.0.0.dist-info/top_level.txt
odoo_addon_product_pricelist_brand_required-17.0.2.0.0.dist-info/RECORD
