Metadata-Version: 2.1
Name: odoo-addon-product_pricelist_brand_required
Version: 17.0.2.0.0
Requires-Python: >=3.10
Requires-Dist: odoo-addon-product_brand>=17.0dev,<17.1dev
Requires-Dist: odoo>=17.0a,<17.1dev
Summary: Check if the product's brand matches any selected brand in the pricelist item.
Home-page: https://github.com/sygel-technology/sy-product-attribute
License: AGPL-3
Author: Sygel,Odoo Community Association (OCA)
Author-email: support@odoo-community.org
Classifier: Programming Language :: Python
Classifier: Framework :: Odoo
Classifier: Framework :: Odoo :: 17.0
Classifier: License :: OSI Approved :: GNU Affero General Public License v3
